LICENSE.txt
MANIFEST.in
README.rst
setup.cfg
setup.py
examples/plot_compare_optimizers.py
examples/plot_held_out_enet.py
examples/plot_held_out_lasso.py
examples/plot_lassoCV.py
examples/plot_meg_lasso_vs_wlasso.py
examples/plot_sparse_log_reg.py
examples/plot_use_callback.py
examples/plot_wlasso.py
sparse_ho/__init__.py
sparse_ho/grid_search.py
sparse_ho/ho.py
sparse_ho/utils.py
sparse_ho/utils_cross_entropy.py
sparse_ho/utils_plot.py
sparse_ho/algo/__init__.py
sparse_ho/algo/backward.py
sparse_ho/algo/base.py
sparse_ho/algo/forward.py
sparse_ho/algo/implicit.py
sparse_ho/algo/implicit_forward.py
sparse_ho/criterion/__init__.py
sparse_ho/criterion/base.py
sparse_ho/criterion/cross_val.py
sparse_ho/criterion/held_out.py
sparse_ho/criterion/multiclass_logreg.py
sparse_ho/criterion/sure.py
sparse_ho/datasets/__init__.py
sparse_ho/datasets/utils_datasets.py
sparse_ho/models/__init__.py
sparse_ho/models/base.py
sparse_ho/models/enet.py
sparse_ho/models/lasso.py
sparse_ho/models/logreg.py
sparse_ho/models/ssvr.py
sparse_ho/models/svm.py
sparse_ho/models/svr.py
sparse_ho/models/wlasso.py
sparse_ho/optimizers/__init__.py
sparse_ho/optimizers/adam.py
sparse_ho/optimizers/base.py
sparse_ho/optimizers/gradient_descent.py
sparse_ho/optimizers/line_search.py
sparse_ho/tests/__init__.py
sparse_ho/tests/common.py
sparse_ho/tests/cvxpylayer.py
sparse_ho/tests/test_criterion.py
sparse_ho/tests/test_docstring_parameters.py
sparse_ho/tests/test_grid_search.py
sparse_ho/tests/test_models.py
sparse_ho/tests/test_multiclass.py
sparse_ho/tests/test_optimizers.py
sparse_ho/tests/test_utils.py
sparse_ho/tests/test_utils_cross_entropy.py
sparse_ho_fork_leoiv.egg-info/PKG-INFO
sparse_ho_fork_leoiv.egg-info/SOURCES.txt
sparse_ho_fork_leoiv.egg-info/dependency_links.txt
sparse_ho_fork_leoiv.egg-info/requires.txt
sparse_ho_fork_leoiv.egg-info/top_level.txt