Metadata-Version: 2.1
Name: sparse-ho-fork-leoiv
Version: 0.1.dev0
Summary: Implicit forward differentiation for Lasso-type problems
Home-page: https://github.com/QB3/sparse-ho
Author: ('Q. Bertrand', 'Q. Klopfenstein')
Author-email: quentin.bertrand@inria.fr
License: BSD
Download-URL: https://github.com/QB3/sparse-ho.git
Platform: any
Classifier: Intended Audience :: Science/Research
Classifier: Intended Audience :: Developers
Classifier: License :: OSI Approved
Classifier: Programming Language :: Python
Classifier: Topic :: Software Development
Classifier: Topic :: Scientific/Engineering
Classifier: Operating System :: Microsoft :: Windows
Classifier: Operating System :: POSIX
Classifier: Operating System :: Unix
Classifier: Operating System :: MacOS
License-File: LICENSE.txt
